WigleSearch.py
wigle_ssid_search-0.1.3.dist-info/METADATA
wigle_ssid_search-0.1.3.dist-info/WHEEL
wigle_ssid_search-0.1.3.dist-info/entry_points.txt
wigle_ssid_search-0.1.3.dist-info/top_level.txt
wigle_ssid_search-0.1.3.dist-info/RECORD
