Metadata-Version: 2.4
Name: wigle-ssid-search
Version: 0.1.3
Summary: Command-line tool for querying the WiGLE API for SSIDs and exporting results as JSON or KML.
Author-email: Defensive Origins <info@defensiveorigins.com>
License: MIT
Project-URL: Homepage, https://github.com/DefensiveOrigins/WigleSSIDSearch
Project-URL: Source, https://github.com/DefensiveOrigins/WigleSSIDSearch
Project-URL: Issues, https://github.com/DefensiveOrigins/WigleSSIDSearch/issues
Keywords: wigle,wifi,wireless,ssid,kml,json,mapping,geolocation
Classifier: Programming Language :: Python
Classifier: Programming Language :: Python :: 3
Classifier: Programming Language :: Python :: 3 :: Only
Classifier: Programming Language :: Python :: 3.7
Classifier: Programming Language :: Python :: 3.8
Classifier: Programming Language :: Python :: 3.9
Classifier: Programming Language :: Python :: 3.10
Classifier: Programming Language :: Python :: 3.11
Classifier: Programming Language :: Python :: 3.12
Classifier: License :: OSI Approved :: MIT License
Classifier: Operating System :: OS Independent
Classifier: Environment :: Console
Classifier: Topic :: Internet
Classifier: Topic :: Utilities
Classifier: Topic :: Scientific/Engineering :: GIS
Requires-Python: >=3.7
Requires-Dist: requests>=2.0.0
